atmosphere/__init__.py
atmosphere/allocation_source.py
atmosphere/group.py
atmosphere/identity.py
atmosphere/image.py
atmosphere/instance.py
atmosphere/main.py
atmosphere/maintenance_record.py
atmosphere/project.py
atmosphere/provider.py
atmosphere/size.py
atmosphere/utils.py
atmosphere/version.py
atmosphere/volume.py
atmosphere/api/__init__.py
atmosphere/api/constants.py
atmosphere/api/main.py
atmosphere/api/request.py
atmosphere/hooks/__init__.py
atmosphere/hooks/delete_hook.py
atmosphere_cli-1.0.0.dist-info/METADATA
atmosphere_cli-1.0.0.dist-info/RECORD
atmosphere_cli-1.0.0.dist-info/WHEEL
atmosphere_cli-1.0.0.dist-info/entry_points.txt
atmosphere_cli-1.0.0.dist-info/pbr.json
atmosphere_cli-1.0.0.dist-info/top_level.txt
