Metadata-Version: 2.1
Name: atmosphere-cli
Version: 1.0.0
Summary: A command-line interface for Atmosphere
Home-page: https://github.com/eriksf/atmosphere-cli
Author: Erik Ferlanti
Author-email: eferlanti@tacc.utexas.edu
License: LICENSE.txt
Keywords: atmosphere
Platform: UNKNOWN
Classifier: Development Status :: 5 - Production/Stable
Classifier: Intended Audience :: Developers
Classifier: Intended Audience :: System Administrators
Classifier: Intended Audience :: Information Technology
Classifier: Intended Audience :: Science/Research
Classifier: License :: OSI Approved :: BSD License
Classifier: Operating System :: OS Independent
Classifier: Programming Language :: Python :: 2.7
Classifier: Programming Language :: Python :: 3
Classifier: Programming Language :: Python :: 3.6
Classifier: Topic :: Software Development :: Libraries
Classifier: Topic :: System
Classifier: Topic :: System :: Clustering
Classifier: Topic :: System :: Distributed Computing
Classifier: Topic :: System :: Systems Administration
Requires-Dist: cliff
Requires-Dist: pbr
Requires-Dist: python-dateutil
Requires-Dist: python-dotenv
Requires-Dist: requests
Requires-Dist: six
